msrestazure/__init__.py
msrestazure/azure_active_directory.py
msrestazure/azure_cloud.py
msrestazure/azure_configuration.py
msrestazure/azure_exceptions.py
msrestazure/azure_operation.py
msrestazure/tools.py
msrestazure/version.py
msrestazure/polling/__init__.py
msrestazure/polling/arm_polling.py
msrestazure/polling/async_arm_polling.py
msrestazure-0.6.4.post1.dist-info/LICENSE.md
msrestazure-0.6.4.post1.dist-info/METADATA
msrestazure-0.6.4.post1.dist-info/WHEEL
msrestazure-0.6.4.post1.dist-info/top_level.txt
msrestazure-0.6.4.post1.dist-info/RECORD
